{"cameraMode":{"drawMode":0,"name":"Shaded","section":"Shading Mode"},"sceneLighting":true,"audioPlay":false,"sceneViewState":{"m_AlwaysRefresh":false,"showFog":true,"showSkybox":true,"showFlares":true,"showImageEffects":true,"showParticleSystems":true,"showVisualEffectGraphs":true,"m_FxEnabled":true},"in2DMode":false,"pivot":{"x":57.87479782104492,"y":13.932184219360352,"z":43.78730010986328},"rotation":{"x":-0.019928671419620515,"y":-0.4862196147441864,"z":0.011092226952314377,"w":-0.8735389113426209},"size":17.721960067749025,"orthographic":false}